{
  "corsDomains" : [
    "gis2.rse-web.it",
    "gis2.rse-web.it:8080"
  ],
  "catalog": [
    {
      "type": "group",
      "name": "General Data - European Level Layers",
      "description": " ",
      "isOpen": false,
      "members": [
        {
          "type": "wms",
          "name": "European Bathymetry",
          "description": "Average depth of the seabed data provided by the EMODnet-Bathymetry services for the European Sea Regions https://emodnet.ec.europa.eu/en/bathymetry#bathymetry-services.",
          "url": "https://ows.emodnet-bathymetry.eu/wms/inspire_quad",
          //"featureInfoTemplate": {
          //  "template": "<p>Consumi registrati (GWh) <b>{{valore}}</b></p><p style='display: block; text-align: center;'> <a href=\"http://dbeta.rse-web.it/atlante_integrato_metadati.php?var_id={{var_id}}&anno={{anno}}\">link al metadato </a><br></p><table width=\"220\" border = \"0\" align='center'><tr><td bgcolor='#519AC2' align='center' disabled><a href=\"http://dbeta.rse-web.it/ai_connessione_db_dati_grafico.php?var_id={{var_id}}&cod_ammin={{cod_reg}}&lingua=IT&limite=reg\"><font color='#FFFFFF'>Visualizza grafico storico</a></font></td></tr></table>"
          //},
          "layers": "emodnet:mean_multicolour",
          "id": "eu_bath"
        },
        {
          "type": "wms",
          "name": "UNESCO Heritage Convention",
          "description": "<p align=\"justify\">UNESCO Heritage Convention</p><p align=\"justify\">Data provided by EMODnet https://emodnet.ec.europa.eu/geoviewer/#!/.</p>",
          "url": "https://gis2.rse-web.it/geoserver/marinewind/wms?service=WMS&version=1.3.0&request=GetMap&layers=marinewind%3unesco_EMODnet",
          //"metadataUrls":[{
          //  "title":"metadata link",
          //  "url":"http://dbeta.rse-web.it/atlante_integrato_metadati.php?var_id=122"
          //}],
          "layers": "marinewind:unesco_EMODnet",
          "id": "generale_unesco"
        },
        {
          "type": "wms",
          "name": "Active Licences EMODnet",
          "description": "<p align=\"justify\">Active Licences EMODnet</p><p align=\"justify\">Data provided by EMODnet https://emodnet.ec.europa.eu/geoviewer/#!/.</p>",
          "url": "https://gis2.rse-web.it/geoserver/marinewind/wms?service=WMS&version=1.3.0&request=GetMap&layers=marinewind%active_licences_emodnet",
          //"metadataUrls":[{
          //  "title":"metadata link",
          //  "url":"http://dbeta.rse-web.it/atlante_integrato_metadati.php?var_id=122"
          //}],
          "layers": "marinewind:active_licences_emodnet",
          "id": "generale_active_licences_emodnet"
        },
        {
          "type": "wms",
          "name": "Offshore Installations EMODnet",
          "description": "<p align=\"justify\">Offshore Installations EMODnet</p><p align=\"justify\">Data provided by EMODnet https://emodnet.ec.europa.eu/geoviewer/#!/.</p>",
          "url": "https://gis2.rse-web.it/geoserver/marinewind/wms?service=WMS&version=1.3.0&request=GetMap&layers=marinewind%offshore_installations_emodnet",
          //"metadataUrls":[{
          //  "title":"metadata link",
          //  "url":"http://dbeta.rse-web.it/atlante_integrato_metadati.php?var_id=122"
          //}],
          "layers": "marinewind:offshore_installations_emodnet",
          "id": "generale_offshore_installations_emodnet"
        },
        {
          "type": "wms",
          "name": "Military Areas EMODnet",
          "description": "<p align=\"justify\">Military Areas EMODnet</p><p align=\"justify\">Data provided by EMODnet https://emodnet.ec.europa.eu/geoviewer/#!/.</p>",
          "url": "https://gis2.rse-web.it/geoserver/marinewind/wms?service=WMS&version=1.3.0&request=GetMap&layers=marinewind%military_areas_emodnet",
          //"metadataUrls":[{
          //  "title":"metadata link",
          //  "url":"http://dbeta.rse-web.it/atlante_integrato_metadati.php?var_id=122"
          //}],
          "layers": "marinewind:military_areas_emodnet",
          "id": "generale_military_areas_emodnet"
        },
        {
          "type": "wms",
          "name": "Telecommunication Cables",
          "description": "<p></p>",
          "url": "https://ows.emodnet-humanactivities.eu/wms?SERVICE=WMS&REQUEST=GetCapabilities&VERSION=1.3.0",
          //"featureInfoTemplate": {
          //  "template": "<p>Consumi registrati (GWh) <b>{{valore}}</b></p><p style='display: block; text-align: center;'> <a href=\"http://dbeta.rse-web.it/atlante_integrato_metadati.php?var_id={{var_id}}&anno={{anno}}\">link al metadato </a><br></p><table width=\"220\" border = \"0\" align='center'><tr><td bgcolor='#519AC2' align='center' disabled><a href=\"http://dbeta.rse-web.it/ai_connessione_db_dati_grafico.php?var_id={{var_id}}&cod_ammin={{cod_reg}}&lingua=IT&limite=reg\"><font color='#FFFFFF'>Visualizza grafico storico</a></font></td></tr></table>"
          //},
          "layers": "telecablesactual",
          "id": "eu_bath1"
        },
        {
          "type": "wms",
          "name": "Biogenic substrate in Europe",
          "description": "<p>Biogenic substrate in Europe</p>",
          "url": "https://ows.emodnet-seabedhabitats.eu/geoserver/emodnet_view/wms?",
          //"featureInfoTemplate": {
          //  "template": "<p>Consumi registrati (GWh) <b>{{valore}}</b></p><p style='display: block; text-align: center;'> <a href=\"http://dbeta.rse-web.it/atlante_integrato_metadati.php?var_id={{var_id}}&anno={{anno}}\">link al metadato </a><br></p><table width=\"220\" border = \"0\" align='center'><tr><td bgcolor='#519AC2' align='center' disabled><a href=\"http://dbeta.rse-web.it/ai_connessione_db_dati_grafico.php?var_id={{var_id}}&cod_ammin={{cod_reg}}&lingua=IT&limite=reg\"><font color='#FFFFFF'>Visualizza grafico storico</a></font></td></tr></table>"
          //},
          "layers": "biogenic_substrate_2023",
          "id": "generale_biogenic_substrate_2023"
        },
        {
          "type": "wms",
          "name": "Route Density (EMSA) Annual Totals",
          "description": "<p></p>",
          "url": "https://ows.emodnet-humanactivities.eu/wms?SERVICE=WMS&REQUEST=GetCapabilities&VERSION=1.3.0",
          //"featureInfoTemplate": {
          //  "template": "<p>Consumi registrati (GWh) <b>{{valore}}</b></p><p style='display: block; text-align: center;'> <a href=\"http://dbeta.rse-web.it/atlante_integrato_metadati.php?var_id={{var_id}}&anno={{anno}}\">link al metadato </a><br></p><table width=\"220\" border = \"0\" align='center'><tr><td bgcolor='#519AC2' align='center' disabled><a href=\"http://dbeta.rse-web.it/ai_connessione_db_dati_grafico.php?var_id={{var_id}}&cod_ammin={{cod_reg}}&lingua=IT&limite=reg\"><font color='#FFFFFF'>Visualizza grafico storico</a></font></td></tr></table>"
          //},
          "layers": "routedensity_allavg",
          "id": "eu_bath2"
        }
       ]
    }
  ]
}